Metadata-Version: 2.1
Name: ablator
Version: 0.1
Summary: Model Ablation Tool-Kit
Home-page: https://iordanis.xyz
Author: Iordanis Fostiropoulos
Author-email: dev@iordanis.xyz
Requires-Python: >3.10
License-File: LICENSE
Requires-Dist: numpy (==1.24.1)
Requires-Dist: pandas (==2.0.0)
Requires-Dist: scikit-learn (==1.2.2)
Requires-Dist: torch (==1.13.1)
Requires-Dist: torchvision (==0.14.1)
Requires-Dist: tqdm (==4.64.1)
Requires-Dist: tensorboard (==2.12.1)
Requires-Dist: matplotlib (==3.7.1)
Requires-Dist: omegaconf (==2.2.3)
Requires-Dist: scipy (==1.10.1)
Requires-Dist: setproctitle (==1.3.2)
Requires-Dist: ray (==2.1.0)
Requires-Dist: pynvml (==11.5.0)
Requires-Dist: optuna (==3.1.1)
Requires-Dist: tabulate (==0.9.0)
Requires-Dist: seaborn (==0.12.2)
Provides-Extra: dev
Requires-Dist: mypy (==1.2.0) ; extra == 'dev'
Requires-Dist: pytest (==7.3.0) ; extra == 'dev'
Requires-Dist: black (==23.3.0) ; extra == 'dev'
Requires-Dist: flake8 (==6.0.0) ; extra == 'dev'
Requires-Dist: pylint (==2.17.2) ; extra == 'dev'
